{
    "title": "0xCD2EA8E6",
    "items": [
        {
            "link": "Auto-Save",
            "name": "0x7678A577"
        },
        {
            "link": "Gameplay_Settings",
            "name": "0x65C3DC40"
        },
        {
            "link": "Money_Settings",
            "name": "0x17DA3B08"
        },
        {
            "link": "Notification-Console-Menu_Settings",
            "name": "0x5A037DE6"
        },
        {
            "link": "Relationship_Settings",
            "name": "0xC68B68C0"
        },
        {
            "link": "Set_Age_Span_Duration",
            "name": "0x9C181D7E"
        }
    ]
}