{
    "items": [
        {
            "link": "Autonomous Mischief",
            "name": "0xAAD9E598"
        },
        {
            "link": "Autonomous =Mean",
            "name": "0x4D7D79AD"
        },
        {
            "link": "Autonomous Proposals",
            "name": "0xB13E0B6A"
        },
        {
            "link": "Autonomous Marriage",
            "name": "0xA000B74D"
        },
        {
            "link": "Autonomous Flirty",
            "name": "0x7F381CC2"
        },
        {
            "link": "Autonomous Repairs",
            "name": "0x08DAB5B3"
        },
        {
            "link": "Autonomous Cleaning",
            "name": "0xD6D1CEB0"
        }
    ],
    "title": "0xBCBE4E4D"
}